tox_appveyor.py
tox_appveyor-0.1.1.dist-info/entry_points.txt
tox_appveyor-0.1.1.dist-info/LICENSE
tox_appveyor-0.1.1.dist-info/WHEEL
tox_appveyor-0.1.1.dist-info/METADATA
tox_appveyor-0.1.1.dist-info/RECORD
