Metadata-Version: 2.1
Name: tox-appveyor
Version: 0.1.1
Summary: Select 32 or 64-bit Python for Tox on Appveyor
Home-page: https://github.com/takluyver/tox_appveyor
License: UNKNOWN
Author: Thomas Kluyver
Author-email: thomas@kluyver.me.uk
Classifier: Framework :: tox
Classifier: License :: OSI Approved :: MIT License
